<duke>
<!--To run this job:  java -classpath ".;c:\duke-1.2\*" RunDukeTestAA vEMPI240.xml -->
<!--TO recompile wrapper:  javac -cp c:\duke-1.2\* RunDukeTestAA.java -->
<!-- -->
<!-- -->
  <schema>
    <threshold>0.99</threshold>
    <maybe-threshold>0.5</maybe-threshold>
    <path>test</path>

	<!-- Match invalid SSN within client with all scrubbed values except phone: DOB,FName,LName, Address1,City,State,Zip,Sex
			Obviously the incoming data (and the master data) need to be scrubbed here and for all subsequent rules. -->
    <property>
      <name>clientKey</name>
	  <comparator>no.priv.garshol.duke.comparators.ExactComparator</comparator>
      <low>0.0</low>
      <high>1</high>
    </property> 
    <property>
      <name>givenName</name> 
      <comparator>no.priv.garshol.duke.comparators.ExactComparator</comparator>
      <low>0.0</low>
      <high>1</high>
    </property>   
    <property>
      <name>familyName</name>
      <comparator>no.priv.garshol.duke.comparators.ExactComparator</comparator>
      <low>0.0</low>
      <high>1</high>
    </property>    
     <property>
      <name>address1</name>
      <comparator>no.priv.garshol.duke.comparators.ExactComparator</comparator>
      <low>0.0</low>
      <high>1</high>
    </property>   
    <property>
      <name>city</name>
      <comparator>no.priv.garshol.duke.comparators.ExactComparator</comparator>
      <low>0.0</low>
      <high>1</high>
    </property>    
	<property>
      <name>postalCode</name>
      <comparator>no.priv.garshol.duke.comparators.ExactComparator</comparator>
      <low>0.0</low>
      <high>1</high>
    </property>    
	<property>
      <name>state</name>
      <comparator>no.priv.garshol.duke.comparators.ExactComparator</comparator>
      <low>0.0</low>
      <high>1</high>
    </property>   
	<property>
      <name>dateOfBirth</name>
      <comparator>no.priv.garshol.duke.comparators.ExactComparator</comparator>
      <low>0.0</low>
      <high>1</high>
    </property>    
	<property>
      <name>sex</name>
      <comparator>no.priv.garshol.duke.comparators.ExactComparator</comparator>
      <low>0.0</low>
      <high>1</high>
    </property>    
  </schema>  
<database class="no.priv.garshol.duke.databases.LuceneDatabase">
    <param name="min-relevance" value="0.99"/>
    <param name="max-search-hits" value="10"/>
    <param name="path" value="lucene-index"/> 
    <param name="fuzzy-search" value="false"/>
</database>
  <!-- ORDER OF THESE GROUPS MATTERS!!! It returns links for topGroup RIGHT JOIN bottomGroup - i.e. no record is returned for a topGroup record that doesnt match a bottomGroup record.
		However, bottomGroup records that don't join to a topGroup record are returned as "non-match" -->
  <group>
	  <csv>
		<param name="input-file" value="e:\data\openempi_test_patients8_500k.csv" />
		<param name="header-line" value="false" />
		
	    <column name="1"
				property="clientKey"/>
		<column name="2"
				property="givenName"/>
		<column name="3"
				property="familyName"/>
		<column name="5"
				property="address1"/>
		<column name="6"
				property="city"/>
		<column name="7"
				cleaner="no.priv.garshol.duke.cleaners.DigitsOnlyCleaner"
				property="postalCode"/>
		<column name="8"
				property="state"/>
		<column name="9"
				property="dateOfBirth"/>
		<column name="13"
				property="sex"/>
	  </csv>
  </group>
  <group>
	  <csv>
		<param name="input-file" value="e:\data\openempi_test_patients11b_5k.csv" />
		<param name="header-line" value="false" />
		
	    <column name="1"
				property="clientKey"/>
		<column name="2"
				property="givenName"/>
		<column name="3"
				property="familyName"/>
		<column name="5"
				property="address1"/>
		<column name="6"
				property="city"/>
		<column name="7"
				cleaner="no.priv.garshol.duke.cleaners.DigitsOnlyCleaner"
				property="postalCode"/>
		<column name="8"
				property="state"/>
		<column name="9"
				property="dateOfBirth"/>
		<column name="13"
				property="sex"/>
	  </csv>
  </group>
</duke>